agenticflow/__inti__.py
agenticflow/agenticflow.py
agenticflow/setup.py
agenticflow-0.1.0.dist-info/METADATA
agenticflow-0.1.0.dist-info/WHEEL
agenticflow-0.1.0.dist-info/RECORD
